{
    "workflow_execution": {
        "tasks": [
            {
                "color": "",
                "compute": {
                    "end": 114.07742005806635,
                    "start": 109.67742005806635
                },
                "execution_host": {
                    "cores": 32,
                    "flop_rate": 1000000000.0,
                    "hostname": "host01",
                    "memory": 268000000000.0
                },
                "failed": -1.0,
                "num_cores_allocated": 1,
                "read": [
                    {
                        "end": 109.67742005806635,
                        "id": "file_0_0",
                        "start": 1.1084536082474228e-18
                    }
                ],
                "task_id": "task_0_0",
                "terminated": -1.0,
                "whole_task": {
                    "end": 130.5290329751613,
                    "start": 1.1084536082474228e-18
                },
                "write": [
                    {
                        "end": 130.5290329751613,
                        "id": "file_0_1",
                        "start": 114.07742005806635
                    }
                ]
            },
            {
                "color": "",
                "compute": {
                    "end": 151.38064590731554,
                    "start": 146.98064590731553
                },
                "execution_host": {
                    "cores": 32,
                    "flop_rate": 1000000000.0,
                    "hostname": "host01",
                    "memory": 268000000000.0
                },
                "failed": -1.0,
                "num_cores_allocated": 1,
                "read": [
                    {
                        "end": 146.98064590731553,
                        "id": "file_0_1",
                        "start": 130.5290329751613
                    }
                ],
                "task_id": "task_0_1",
                "terminated": -1.0,
                "whole_task": {
                    "end": 229.878794922797,
                    "start": 130.5290329751613
                },
                "write": [
                    {
                        "end": 229.878794922797,
                        "id": "file_0_2",
                        "start": 151.38064590731554
                    }
                ]
            },
            {
                "color": "",
                "compute": {
                    "end": 249.98202364419564,
                    "start": 245.58202364419563
                },
                "execution_host": {
                    "cores": 32,
                    "flop_rate": 1000000000.0,
                    "hostname": "host01",
                    "memory": 268000000000.0
                },
                "failed": -1.0,
                "num_cores_allocated": 1,
                "read": [
                    {
                        "end": 245.58202364419563,
                        "id": "file_0_2",
                        "start": 229.878794922797
                    }
                ],
                "task_id": "task_0_2",
                "terminated": -1.0,
                "whole_task": {
                    "end": 329.7449390809681,
                    "start": 229.878794922797
                },
                "write": [
                    {
                        "end": 329.7449390809681,
                        "id": "file_0_3",
                        "start": 249.98202364419564
                    }
                ]
            },
            {
                "color": "",
                "compute": {
                    "end": 114.07742005806635,
                    "start": 109.67742005806635
                },
                "execution_host": {
                    "cores": 32,
                    "flop_rate": 1000000000.0,
                    "hostname": "host01",
                    "memory": 268000000000.0
                },
                "failed": -1.0,
                "num_cores_allocated": 1,
                "read": [
                    {
                        "end": 109.67742005806635,
                        "id": "file_10_0",
                        "start": 5.542268041237114e-18
                    }
                ],
                "task_id": "task_10_0",
                "terminated": -1.0,
                "whole_task": {
                    "end": 130.5290329751613,
                    "start": 5.542268041237114e-18
                },
                "write": [
                    {
                        "end": 130.5290329751613,
                        "id": "file_10_1",
                        "start": 114.07742005806635
                    }
                ]
            },
            {
                "color": "",
                "compute": {
                    "end": 151.38064590731554,
                    "start": 146.98064590731553
                },
                "execution_host": {
                    "cores": 32,
                    "flop_rate": 1000000000.0,
                    "hostname": "host01",
                    "memory": 268000000000.0
                },
                "failed": -1.0,
                "num_cores_allocated": 1,
                "read": [
                    {
                        "end": 146.98064590731553,
                        "id": "file_10_1",
                        "start": 130.5290329751613
                    }
                ],
                "task_id": "task_10_1",
                "terminated": -1.0,
                "whole_task": {
                    "end": 229.878794922797,
                    "start": 130.5290329751613
                },
                "write": [
                    {
                        "end": 229.878794922797,
                        "id": "file_10_2",
                        "start": 151.38064590731554
                    }
                ]
            },
            {
                "color": "",
                "compute": {
                    "end": 249.98202364419564,
                    "start": 245.58202364419563
                },
                "execution_host": {
                    "cores": 32,
                    "flop_rate": 1000000000.0,
                    "hostname": "host01",
                    "memory": 268000000000.0
                },
                "failed": -1.0,
                "num_cores_allocated": 1,
                "read": [
                    {
                        "end": 245.58202364419563,
                        "id": "file_10_2",
                        "start": 229.878794922797
                    }
                ],
                "task_id": "task_10_2",
                "terminated": -1.0,
                "whole_task": {
                    "end": 329.73016486193586,
                    "start": 229.878794922797
                },
                "write": [
                    {
                        "end": 329.73016486193586,
                        "id": "file_10_3",
                        "start": 249.98202364419564
                    }
                ]
            },
            {
                "color": "",
                "compute": {
                    "end": 114.07742005806635,
                    "start": 109.67742005806635
                },
                "execution_host": {
                    "cores": 32,
                    "flop_rate": 1000000000.0,
                    "hostname": "host01",
                    "memory": 268000000000.0
                },
                "failed": -1.0,
                "num_cores_allocated": 1,
                "read": [
                    {
                        "end": 109.67742005806635,
                        "id": "file_11_0",
                        "start": 9.976082474226805e-18
                    }
                ],
                "task_id": "task_11_0",
                "terminated": -1.0,
                "whole_task": {
                    "end": 130.5290329751613,
                    "start": 9.976082474226805e-18
                },
                "write": [
                    {
                        "end": 130.5290329751613,
                        "id": "file_11_1",
                        "start": 114.07742005806635
                    }
                ]
            },
            {
                "color": "",
                "compute": {
                    "end": 151.38064590731554,
                    "start": 146.98064590731553
                },
                "execution_host": {
                    "cores": 32,
                    "flop_rate": 1000000000.0,
                    "hostname": "host01",
                    "memory": 268000000000.0
                },
                "failed": -1.0,
                "num_cores_allocated": 1,
                "read": [
                    {
                        "end": 146.98064590731553,
                        "id": "file_11_1",
                        "start": 130.5290329751613
                    }
                ],
                "task_id": "task_11_1",
                "terminated": -1.0,
                "whole_task": {
                    "end": 229.8787297195712,
                    "start": 130.5290329751613
                },
                "write": [
                    {
                        "end": 229.8787297195712,
                        "id": "file_11_2",
                        "start": 151.38064590731554
                    }
                ]
            },
            {
                "color": "",
                "compute": {
                    "end": 249.98200063129218,
                    "start": 245.58200063129217
                },
                "execution_host": {
                    "cores": 32,
                    "flop_rate": 1000000000.0,
                    "hostname": "host01",
                    "memory": 268000000000.0
                },
                "failed": -1.0,
                "num_cores_allocated": 1,
                "read": [
                    {
                        "end": 245.58200063129217,
                        "id": "file_11_2",
                        "start": 229.8787297195712
                    }
                ],
                "task_id": "task_11_2",
                "terminated": -1.0,
                "whole_task": {
                    "end": 329.75302285129067,
                    "start": 229.8787297195712
                },
                "write": [
                    {
                        "end": 329.75302285129067,
                        "id": "file_11_3",
                        "start": 249.98200063129218
                    }
                ]
            },
            {
                "color": "",
                "compute": {
                    "end": 114.07742005806635,
                    "start": 109.67742005806635
                },
                "execution_host": {
                    "cores": 32,
                    "flop_rate": 1000000000.0,
                    "hostname": "host01",
                    "memory": 268000000000.0
                },
                "failed": -1.0,
                "num_cores_allocated": 1,
                "read": [
                    {
                        "end": 109.67742005806635,
                        "id": "file_12_0",
                        "start": 1.4409896907216497e-17
                    }
                ],
                "task_id": "task_12_0",
                "terminated": -1.0,
                "whole_task": {
                    "end": 130.5290329751613,
                    "start": 1.4409896907216497e-17
                },
                "write": [
                    {
                        "end": 130.5290329751613,
                        "id": "file_12_1",
                        "start": 114.07742005806635
                    }
                ]
            },
            {
                "color": "",
                "compute": {
                    "end": 151.38064590731554,
                    "start": 146.98064590731553
                },
                "execution_host": {
                    "cores": 32,
                    "flop_rate": 1000000000.0,
                    "hostname": "host01",
                    "memory": 268000000000.0
                },
                "failed": -1.0,
                "num_cores_allocated": 1,
                "read": [
                    {
                        "end": 146.98064590731553,
                        "id": "file_12_1",
                        "start": 130.5290329751613
                    }
                ],
                "task_id": "task_12_1",
                "terminated": -1.0,
                "whole_task": {
                    "end": 229.35108903709735,
                    "start": 130.5290329751613
                },
                "write": [
                    {
                        "end": 229.35108903709735,
                        "id": "file_12_2",
                        "start": 151.38064590731554
                    }
                ]
            },
            {
                "color": "",
                "compute": {
                    "end": 249.72463493258158,
                    "start": 245.32463493258157
                },
                "execution_host": {
                    "cores": 32,
                    "flop_rate": 1000000000.0,
                    "hostname": "host01",
                    "memory": 268000000000.0
                },
                "failed": -1.0,
                "num_cores_allocated": 1,
                "read": [
                    {
                        "end": 245.32463493258157,
                        "id": "file_12_2",
                        "start": 229.35108903709735
                    }
                ],
                "task_id": "task_12_2",
                "terminated": -1.0,
                "whole_task": {
                    "end": 328.35671035451674,
                    "start": 229.35108903709735
                },
                "write": [
                    {
                        "end": 328.35671035451674,
                        "id": "file_12_3",
                        "start": 249.72463493258158
                    }
                ]
            },
            {
                "color": "",
                "compute": {
                    "end": 114.07742005806635,
                    "start": 109.67742005806635
                },
                "execution_host": {
                    "cores": 32,
                    "flop_rate": 1000000000.0,
                    "hostname": "host01",
                    "memory": 268000000000.0
                },
                "failed": -1.0,
                "num_cores_allocated": 1,
                "read": [
                    {
                        "end": 109.67742005806635,
                        "id": "file_13_0",
                        "start": 1.8843711340206188e-17
                    }
                ],
                "task_id": "task_13_0",
                "terminated": -1.0,
                "whole_task": {
                    "end": 130.5290329751613,
                    "start": 1.8843711340206188e-17
                },
                "write": [
                    {
                        "end": 130.5290329751613,
                        "id": "file_13_1",
                        "start": 114.07742005806635
                    }
                ]
            },
            {
                "color": "",
                "compute": {
                    "end": 151.38064590731554,
                    "start": 146.98064590731553
                },
                "execution_host": {
                    "cores": 32,
                    "flop_rate": 1000000000.0,
                    "hostname": "host01",
                    "memory": 268000000000.0
                },
                "failed": -1.0,
                "num_cores_allocated": 1,
                "read": [
                    {
                        "end": 146.98064590731553,
                        "id": "file_13_1",
                        "start": 130.5290329751613
                    }
                ],
                "task_id": "task_13_1",
                "terminated": -1.0,
                "whole_task": {
                    "end": 229.0707153864516,
                    "start": 130.5290329751613
                },
                "write": [
                    {
                        "end": 229.0707153864516,
                        "id": "file_13_2",
                        "start": 151.38064590731554
                    }
                ]
            },
            {
                "color": "",
                "compute": {
                    "end": 249.5057269380649,
                    "start": 245.1057269380649
                },
                "execution_host": {
                    "cores": 32,
                    "flop_rate": 1000000000.0,
                    "hostname": "host01",
                    "memory": 268000000000.0
                },
                "failed": -1.0,
                "num_cores_allocated": 1,
                "read": [
                    {
                        "end": 245.1057269380649,
                        "id": "file_13_2",
                        "start": 229.0707153864516
                    }
                ],
                "task_id": "task_13_2",
                "terminated": -1.0,
                "whole_task": {
                    "end": 330.21641689451627,
                    "start": 229.0707153864516
                },
                "write": [
                    {
                        "end": 330.21641689451627,
                        "id": "file_13_3",
                        "start": 249.5057269380649
                    }
                ]
            },
            {
                "color": "",
                "compute": {
                    "end": 114.07742005806635,
                    "start": 109.67742005806635
                },
                "execution_host": {
                    "cores": 32,
                    "flop_rate": 1000000000.0,
                    "hostname": "host01",
                    "memory": 268000000000.0
                },
                "failed": -1.0,
                "num_cores_allocated": 1,
                "read": [
                    {
                        "end": 109.67742005806635,
                        "id": "file_14_0",
                        "start": 2.327752577319588e-17
                    }
                ],
                "task_id": "task_14_0",
                "terminated": -1.0,
                "whole_task": {
                    "end": 130.5290329751613,
                    "start": 2.327752577319588e-17
                },
                "write": [
                    {
                        "end": 130.5290329751613,
                        "id": "file_14_1",
                        "start": 114.07742005806635
                    }
                ]
            },
            {
                "color": "",
                "compute": {
                    "end": 151.38064590731554,
                    "start": 146.98064590731553
                },
                "execution_host": {
                    "cores": 32,
                    "flop_rate": 1000000000.0,
                    "hostname": "host01",
                    "memory": 268000000000.0
                },
                "failed": -1.0,
                "num_cores_allocated": 1,
                "read": [
                    {
                        "end": 146.98064590731553,
                        "id": "file_14_1",
                        "start": 130.5290329751613
                    }
                ],
                "task_id": "task_14_1",
                "terminated": -1.0,
                "whole_task": {
                    "end": 228.8685177070976,
                    "start": 130.5290329751613
                },
                "write": [
                    {
                        "end": 228.8685177070976,
                        "id": "file_14_2",
                        "start": 151.38064590731554
                    }
                ]
            },
            {
                "color": "",
                "compute": {
                    "end": 249.29578408376682,
                    "start": 244.8957840837668
                },
                "execution_host": {
                    "cores": 32,
                    "flop_rate": 1000000000.0,
                    "hostname": "host01",
                    "memory": 268000000000.0
                },
                "failed": -1.0,
                "num_cores_allocated": 1,
                "read": [
                    {
                        "end": 244.8957840837668,
                        "id": "file_14_2",
                        "start": 228.8685177070976
                    }
                ],
                "task_id": "task_14_2",
                "terminated": -1.0,
                "whole_task": {
                    "end": 328.25822919741967,
                    "start": 228.8685177070976
                },
                "write": [
                    {
                        "end": 328.25822919741967,
                        "id": "file_14_3",
                        "start": 249.29578408376682
                    }
                ]
            },
            {
                "color": "",
                "compute": {
                    "end": 114.07742005806635,
                    "start": 109.67742005806635
                },
                "execution_host": {
                    "cores": 32,
                    "flop_rate": 1000000000.0,
                    "hostname": "host01",
                    "memory": 268000000000.0
                },
                "failed": -1.0,
                "num_cores_allocated": 1,
                "read": [
                    {
                        "end": 109.67742005806635,
                        "id": "file_15_0",
                        "start": 2.771134020618557e-17
                    }
                ],
                "task_id": "task_15_0",
                "terminated": -1.0,
                "whole_task": {
                    "end": 130.5290329751613,
                    "start": 2.771134020618557e-17
                },
                "write": [
                    {
                        "end": 130.5290329751613,
                        "id": "file_15_1",
                        "start": 114.07742005806635
                    }
                ]
            },
            {
                "color": "",
                "compute": {
                    "end": 151.38064590731554,
                    "start": 146.98064590731553
                },
                "execution_host": {
                    "cores": 32,
                    "flop_rate": 1000000000.0,
                    "hostname": "host01",
                    "memory": 268000000000.0
                },
                "failed": -1.0,
                "num_cores_allocated": 1,
                "read": [
                    {
                        "end": 146.98064590731553,
                        "id": "file_15_1",
                        "start": 130.5290329751613
                    }
                ],
                "task_id": "task_15_1",
                "terminated": -1.0,
                "whole_task": {
                    "end": 228.82228721548447,
                    "start": 130.5290329751613
                },
                "write": [
                    {
                        "end": 228.82228721548447,
                        "id": "file_15_2",
                        "start": 151.38064590731554
                    }
                ]
            },
            {
                "color": "",
                "compute": {
                    "end": 249.19561801860542,
                    "start": 244.7956180186054
                },
                "execution_host": {
                    "cores": 32,
                    "flop_rate": 1000000000.0,
                    "hostname": "host01",
                    "memory": 268000000000.0
                },
                "failed": -1.0,
                "num_cores_allocated": 1,
                "read": [
                    {
                        "end": 244.7956180186054,
                        "id": "file_15_2",
                        "start": 228.82228721548447
                    }
                ],
                "task_id": "task_15_2",
                "terminated": -1.0,
                "whole_task": {
                    "end": 328.1547232535485,
                    "start": 228.82228721548447
                },
                "write": [
                    {
                        "end": 328.1547232535485,
                        "id": "file_15_3",
                        "start": 249.19561801860542
                    }
                ]
            },
            {
                "color": "",
                "compute": {
                    "end": 114.07742005806635,
                    "start": 109.67742005806635
                },
                "execution_host": {
                    "cores": 32,
                    "flop_rate": 1000000000.0,
                    "hostname": "host01",
                    "memory": 268000000000.0
                },
                "failed": -1.0,
                "num_cores_allocated": 1,
                "read": [
                    {
                        "end": 109.67742005806635,
                        "id": "file_16_0",
                        "start": 3.214515463917526e-17
                    }
                ],
                "task_id": "task_16_0",
                "terminated": -1.0,
                "whole_task": {
                    "end": 130.5290329751613,
                    "start": 3.214515463917526e-17
                },
                "write": [
                    {
                        "end": 130.5290329751613,
                        "id": "file_16_1",
                        "start": 114.07742005806635
                    }
                ]
            },
            {
                "color": "",
                "compute": {
                    "end": 151.38064590731554,
                    "start": 146.98064590731553
                },
                "execution_host": {
                    "cores": 32,
                    "flop_rate": 1000000000.0,
                    "hostname": "host01",
                    "memory": 268000000000.0
                },
                "failed": -1.0,
                "num_cores_allocated": 1,
                "read": [
                    {
                        "end": 146.98064590731553,
                        "id": "file_16_1",
                        "start": 130.5290329751613
                    }
                ],
                "task_id": "task_16_1",
                "terminated": -1.0,
                "whole_task": {
                    "end": 228.81318011935542,
                    "start": 130.5290329751613
                },
                "write": [
                    {
                        "end": 228.81318011935542,
                        "id": "file_16_2",
                        "start": 151.38064590731554
                    }
                ]
            },
            {
                "color": "",
                "compute": {
                    "end": 249.17436812634722,
                    "start": 244.7743681263472
                },
                "execution_host": {
                    "cores": 32,
                    "flop_rate": 1000000000.0,
                    "hostname": "host01",
                    "memory": 268000000000.0
                },
                "failed": -1.0,
                "num_cores_allocated": 1,
                "read": [
                    {
                        "end": 244.7743681263472,
                        "id": "file_16_2",
                        "start": 228.81318011935542
                    }
                ],
                "task_id": "task_16_2",
                "terminated": -1.0,
                "whole_task": {
                    "end": 328.1491261661292,
                    "start": 228.81318011935542
                },
                "write": [
                    {
                        "end": 328.1491261661292,
                        "id": "file_16_3",
                        "start": 249.17436812634722
                    }
                ]
            },
            {
                "color": "",
                "compute": {
                    "end": 114.07742005806635,
                    "start": 109.67742005806635
                },
                "execution_host": {
                    "cores": 32,
                    "flop_rate": 1000000000.0,
                    "hostname": "host01",
                    "memory": 268000000000.0
                },
                "failed": -1.0,
                "num_cores_allocated": 1,
                "read": [
                    {
                        "end": 109.67742005806635,
                        "id": "file_1_0",
                        "start": 3.657896907216495e-17
                    }
                ],
                "task_id": "task_1_0",
                "terminated": -1.0,
                "whole_task": {
                    "end": 130.5290329751613,
                    "start": 3.657896907216495e-17
                },
                "write": [
                    {
                        "end": 130.5290329751613,
                        "id": "file_1_1",
                        "start": 114.07742005806635
                    }
                ]
            },
            {
                "color": "",
                "compute": {
                    "end": 151.38064590731554,
                    "start": 146.98064590731553
                },
                "execution_host": {
                    "cores": 32,
                    "flop_rate": 1000000000.0,
                    "hostname": "host01",
                    "memory": 268000000000.0
                },
                "failed": -1.0,
                "num_cores_allocated": 1,
                "read": [
                    {
                        "end": 146.98064590731553,
                        "id": "file_1_1",
                        "start": 130.5290329751613
                    }
                ],
                "task_id": "task_1_1",
                "terminated": -1.0,
                "whole_task": {
                    "end": 229.88783476053905,
                    "start": 130.5290329751613
                },
                "write": [
                    {
                        "end": 229.88783476053905,
                        "id": "file_1_2",
                        "start": 151.38064590731554
                    }
                ]
            },
            {
                "color": "",
                "compute": {
                    "end": 249.98363016322813,
                    "start": 245.58363016322812
                },
                "execution_host": {
                    "cores": 32,
                    "flop_rate": 1000000000.0,
                    "hostname": "host01",
                    "memory": 268000000000.0
                },
                "failed": -1.0,
                "num_cores_allocated": 1,
                "read": [
                    {
                        "end": 245.58363016322812,
                        "id": "file_1_2",
                        "start": 229.88783476053905
                    }
                ],
                "task_id": "task_1_2",
                "terminated": -1.0,
                "whole_task": {
                    "end": 330.2506157309679,
                    "start": 229.88783476053905
                },
                "write": [
                    {
                        "end": 330.2506157309679,
                        "id": "file_1_3",
                        "start": 249.98363016322813
                    }
                ]
            },
            {
                "color": "",
                "compute": {
                    "end": 114.07742005806635,
                    "start": 109.67742005806635
                },
                "execution_host": {
                    "cores": 32,
                    "flop_rate": 1000000000.0,
                    "hostname": "host01",
                    "memory": 268000000000.0
                },
                "failed": -1.0,
                "num_cores_allocated": 1,
                "read": [
                    {
                        "end": 109.67742005806635,
                        "id": "file_2_0",
                        "start": 4.1012783505154644e-17
                    }
                ],
                "task_id": "task_2_0",
                "terminated": -1.0,
                "whole_task": {
                    "end": 130.5290329751613,
                    "start": 4.1012783505154644e-17
                },
                "write": [
                    {
                        "end": 130.5290329751613,
                        "id": "file_2_1",
                        "start": 114.07742005806635
                    }
                ]
            },
            {
                "color": "",
                "compute": {
                    "end": 151.38064590731554,
                    "start": 146.98064590731553
                },
                "execution_host": {
                    "cores": 32,
                    "flop_rate": 1000000000.0,
                    "hostname": "host01",
                    "memory": 268000000000.0
                },
                "failed": -1.0,
                "num_cores_allocated": 1,
                "read": [
                    {
                        "end": 146.98064590731553,
                        "id": "file_2_1",
                        "start": 130.5290329751613
                    }
                ],
                "task_id": "task_2_1",
                "terminated": -1.0,
                "whole_task": {
                    "end": 229.8789862331197,
                    "start": 130.5290329751613
                },
                "write": [
                    {
                        "end": 229.8789862331197,
                        "id": "file_2_2",
                        "start": 151.38064590731554
                    }
                ]
            },
            {
                "color": "",
                "compute": {
                    "end": 249.9820686583893,
                    "start": 245.5820686583893
                },
                "execution_host": {
                    "cores": 32,
                    "flop_rate": 1000000000.0,
                    "hostname": "host01",
                    "memory": 268000000000.0
                },
                "failed": -1.0,
                "num_cores_allocated": 1,
                "read": [
                    {
                        "end": 245.5820686583893,
                        "id": "file_2_2",
                        "start": 229.8789862331197
                    }
                ],
                "task_id": "task_2_2",
                "terminated": -1.0,
                "whole_task": {
                    "end": 329.7763141941939,
                    "start": 229.8789862331197
                },
                "write": [
                    {
                        "end": 329.7763141941939,
                        "id": "file_2_3",
                        "start": 249.9820686583893
                    }
                ]
            },
            {
                "color": "",
                "compute": {
                    "end": 114.07742005806635,
                    "start": 109.67742005806635
                },
                "execution_host": {
                    "cores": 32,
                    "flop_rate": 1000000000.0,
                    "hostname": "host01",
                    "memory": 268000000000.0
                },
                "failed": -1.0,
                "num_cores_allocated": 1,
                "read": [
                    {
                        "end": 109.67742005806635,
                        "id": "file_3_0",
                        "start": 4.5446597938144336e-17
                    }
                ],
                "task_id": "task_3_0",
                "terminated": -1.0,
                "whole_task": {
                    "end": 130.5290329751613,
                    "start": 4.5446597938144336e-17
                },
                "write": [
                    {
                        "end": 130.5290329751613,
                        "id": "file_3_1",
                        "start": 114.07742005806635
                    }
                ]
            },
            {
                "color": "",
                "compute": {
                    "end": 151.38064590731554,
                    "start": 146.98064590731553
                },
                "execution_host": {
                    "cores": 32,
                    "flop_rate": 1000000000.0,
                    "hostname": "host01",
                    "memory": 268000000000.0
                },
                "failed": -1.0,
                "num_cores_allocated": 1,
                "read": [
                    {
                        "end": 146.98064590731553,
                        "id": "file_3_1",
                        "start": 130.5290329751613
                    }
                ],
                "task_id": "task_3_1",
                "terminated": -1.0,
                "whole_task": {
                    "end": 229.35946067258124,
                    "start": 130.5290329751613
                },
                "write": [
                    {
                        "end": 229.35946067258124,
                        "id": "file_3_2",
                        "start": 151.38064590731554
                    }
                ]
            },
            {
                "color": "",
                "compute": {
                    "end": 249.73019751516267,
                    "start": 245.33019751516267
                },
                "execution_host": {
                    "cores": 32,
                    "flop_rate": 1000000000.0,
                    "hostname": "host01",
                    "memory": 268000000000.0
                },
                "failed": -1.0,
                "num_cores_allocated": 1,
                "read": [
                    {
                        "end": 245.33019751516267,
                        "id": "file_3_2",
                        "start": 229.35946067258124
                    }
                ],
                "task_id": "task_3_2",
                "terminated": -1.0,
                "whole_task": {
                    "end": 322.8429539784948,
                    "start": 229.35946067258124
                },
                "write": [
                    {
                        "end": 322.8429539784948,
                        "id": "file_3_3",
                        "start": 249.73019751516267
                    }
                ]
            },
            {
                "color": "",
                "compute": {
                    "end": 114.07742005806635,
                    "start": 109.67742005806635
                },
                "execution_host": {
                    "cores": 32,
                    "flop_rate": 1000000000.0,
                    "hostname": "host01",
                    "memory": 268000000000.0
                },
                "failed": -1.0,
                "num_cores_allocated": 1,
                "read": [
                    {
                        "end": 109.67742005806635,
                        "id": "file_4_0",
                        "start": 4.9880412371134027e-17
                    }
                ],
                "task_id": "task_4_0",
                "terminated": -1.0,
                "whole_task": {
                    "end": 130.5290329751613,
                    "start": 4.9880412371134027e-17
                },
                "write": [
                    {
                        "end": 130.5290329751613,
                        "id": "file_4_1",
                        "start": 114.07742005806635
                    }
                ]
            },
            {
                "color": "",
                "compute": {
                    "end": 151.38064590731554,
                    "start": 146.98064590731553
                },
                "execution_host": {
                    "cores": 32,
                    "flop_rate": 1000000000.0,
                    "hostname": "host01",
                    "memory": 268000000000.0
                },
                "failed": -1.0,
                "num_cores_allocated": 1,
                "read": [
                    {
                        "end": 146.98064590731553,
                        "id": "file_4_1",
                        "start": 130.5290329751613
                    }
                ],
                "task_id": "task_4_1",
                "terminated": -1.0,
                "whole_task": {
                    "end": 228.43622782150538,
                    "start": 130.5290329751613
                },
                "write": [
                    {
                        "end": 228.43622782150538,
                        "id": "file_4_2",
                        "start": 151.38064590731554
                    }
                ]
            },
            {
                "color": "",
                "compute": {
                    "end": 247.75983216086198,
                    "start": 243.35983216086197
                },
                "execution_host": {
                    "cores": 32,
                    "flop_rate": 1000000000.0,
                    "hostname": "host01",
                    "memory": 268000000000.0
                },
                "failed": -1.0,
                "num_cores_allocated": 1,
                "read": [
                    {
                        "end": 243.35983216086197,
                        "id": "file_4_2",
                        "start": 228.43622782150538
                    }
                ],
                "task_id": "task_4_2",
                "terminated": -1.0,
                "whole_task": {
                    "end": 249.50485366871365,
                    "start": 228.43622782150538
                },
                "write": [
                    {
                        "end": 249.50485366871365,
                        "id": "file_4_3",
                        "start": 247.75983216086198
                    }
                ]
            },
            {
                "color": "",
                "compute": {
                    "end": 114.07742005806635,
                    "start": 109.67742005806635
                },
                "execution_host": {
                    "cores": 32,
                    "flop_rate": 1000000000.0,
                    "hostname": "host01",
                    "memory": 268000000000.0
                },
                "failed": -1.0,
                "num_cores_allocated": 1,
                "read": [
                    {
                        "end": 109.67742005806635,
                        "id": "file_5_0",
                        "start": 5.431422680412372e-17
                    }
                ],
                "task_id": "task_5_0",
                "terminated": -1.0,
                "whole_task": {
                    "end": 130.5290329751613,
                    "start": 5.431422680412372e-17
                },
                "write": [
                    {
                        "end": 130.5290329751613,
                        "id": "file_5_1",
                        "start": 114.07742005806635
                    }
                ]
            },
            {
                "color": "",
                "compute": {
                    "end": 151.38064590731554,
                    "start": 146.98064590731553
                },
                "execution_host": {
                    "cores": 32,
                    "flop_rate": 1000000000.0,
                    "hostname": "host01",
                    "memory": 268000000000.0
                },
                "failed": -1.0,
                "num_cores_allocated": 1,
                "read": [
                    {
                        "end": 146.98064590731553,
                        "id": "file_5_1",
                        "start": 130.5290329751613
                    }
                ],
                "task_id": "task_5_1",
                "terminated": -1.0,
                "whole_task": {
                    "end": 228.38314446215054,
                    "start": 130.5290329751613
                },
                "write": [
                    {
                        "end": 228.38314446215054,
                        "id": "file_5_2",
                        "start": 151.38064590731554
                    }
                ]
            },
            {
                "color": "",
                "compute": {
                    "end": 247.3351652854865,
                    "start": 242.9351652854865
                },
                "execution_host": {
                    "cores": 32,
                    "flop_rate": 1000000000.0,
                    "hostname": "host01",
                    "memory": 268000000000.0
                },
                "failed": -1.0,
                "num_cores_allocated": 1,
                "read": [
                    {
                        "end": 242.9351652854865,
                        "id": "file_5_2",
                        "start": 228.38314446215054
                    }
                ],
                "task_id": "task_5_2",
                "terminated": -1.0,
                "whole_task": {
                    "end": 248.84598228150816,
                    "start": 228.38314446215054
                },
                "write": [
                    {
                        "end": 248.84598228150816,
                        "id": "file_5_3",
                        "start": 247.3351652854865
                    }
                ]
            },
            {
                "color": "",
                "compute": {
                    "end": 114.07742005806635,
                    "start": 109.67742005806635
                },
                "execution_host": {
                    "cores": 32,
                    "flop_rate": 1000000000.0,
                    "hostname": "host01",
                    "memory": 268000000000.0
                },
                "failed": -1.0,
                "num_cores_allocated": 1,
                "read": [
                    {
                        "end": 109.67742005806635,
                        "id": "file_6_0",
                        "start": 5.87480412371134e-17
                    }
                ],
                "task_id": "task_6_0",
                "terminated": -1.0,
                "whole_task": {
                    "end": 130.5290329751613,
                    "start": 5.87480412371134e-17
                },
                "write": [
                    {
                        "end": 130.5290329751613,
                        "id": "file_6_1",
                        "start": 114.07742005806635
                    }
                ]
            },
            {
                "color": "",
                "compute": {
                    "end": 151.38064590731554,
                    "start": 146.98064590731553
                },
                "execution_host": {
                    "cores": 32,
                    "flop_rate": 1000000000.0,
                    "hostname": "host01",
                    "memory": 268000000000.0
                },
                "failed": -1.0,
                "num_cores_allocated": 1,
                "read": [
                    {
                        "end": 146.98064590731553,
                        "id": "file_6_1",
                        "start": 130.5290329751613
                    }
                ],
                "task_id": "task_6_1",
                "terminated": -1.0,
                "whole_task": {
                    "end": 230.06253315096774,
                    "start": 130.5290329751613
                },
                "write": [
                    {
                        "end": 230.06253315096774,
                        "id": "file_6_2",
                        "start": 151.38064590731554
                    }
                ]
            },
            {
                "color": "",
                "compute": {
                    "end": 250.00323457548643,
                    "start": 245.60323457548643
                },
                "execution_host": {
                    "cores": 32,
                    "flop_rate": 1000000000.0,
                    "hostname": "host01",
                    "memory": 268000000000.0
                },
                "failed": -1.0,
                "num_cores_allocated": 1,
                "read": [
                    {
                        "end": 245.60323457548643,
                        "id": "file_6_2",
                        "start": 230.06253315096774
                    }
                ],
                "task_id": "task_6_2",
                "terminated": -1.0,
                "whole_task": {
                    "end": 330.1513138338711,
                    "start": 230.06253315096774
                },
                "write": [
                    {
                        "end": 330.1513138338711,
                        "id": "file_6_3",
                        "start": 250.00323457548643
                    }
                ]
            },
            {
                "color": "",
                "compute": {
                    "end": 114.07742005806635,
                    "start": 109.67742005806635
                },
                "execution_host": {
                    "cores": 32,
                    "flop_rate": 1000000000.0,
                    "hostname": "host01",
                    "memory": 268000000000.0
                },
                "failed": -1.0,
                "num_cores_allocated": 1,
                "read": [
                    {
                        "end": 109.67742005806635,
                        "id": "file_7_0",
                        "start": 6.31818556701031e-17
                    }
                ],
                "task_id": "task_7_0",
                "terminated": -1.0,
                "whole_task": {
                    "end": 130.5290329751613,
                    "start": 6.31818556701031e-17
                },
                "write": [
                    {
                        "end": 130.5290329751613,
                        "id": "file_7_1",
                        "start": 114.07742005806635
                    }
                ]
            },
            {
                "color": "",
                "compute": {
                    "end": 151.38064590731554,
                    "start": 146.98064590731553
                },
                "execution_host": {
                    "cores": 32,
                    "flop_rate": 1000000000.0,
                    "hostname": "host01",
                    "memory": 268000000000.0
                },
                "failed": -1.0,
                "num_cores_allocated": 1,
                "read": [
                    {
                        "end": 146.98064590731553,
                        "id": "file_7_1",
                        "start": 130.5290329751613
                    }
                ],
                "task_id": "task_7_1",
                "terminated": -1.0,
                "whole_task": {
                    "end": 230.04641137096775,
                    "start": 130.5290329751613
                },
                "write": [
                    {
                        "end": 230.04641137096775,
                        "id": "file_7_2",
                        "start": 151.38064590731554
                    }
                ]
            },
            {
                "color": "",
                "compute": {
                    "end": 250.0022862354863,
                    "start": 245.6022862354863
                },
                "execution_host": {
                    "cores": 32,
                    "flop_rate": 1000000000.0,
                    "hostname": "host01",
                    "memory": 268000000000.0
                },
                "failed": -1.0,
                "num_cores_allocated": 1,
                "read": [
                    {
                        "end": 245.6022862354863,
                        "id": "file_7_2",
                        "start": 230.04641137096775
                    }
                ],
                "task_id": "task_7_2",
                "terminated": -1.0,
                "whole_task": {
                    "end": 330.1381337048387,
                    "start": 230.04641137096775
                },
                "write": [
                    {
                        "end": 330.1381337048387,
                        "id": "file_7_3",
                        "start": 250.0022862354863
                    }
                ]
            },
            {
                "color": "",
                "compute": {
                    "end": 114.07742005806635,
                    "start": 109.67742005806635
                },
                "execution_host": {
                    "cores": 32,
                    "flop_rate": 1000000000.0,
                    "hostname": "host01",
                    "memory": 268000000000.0
                },
                "failed": -1.0,
                "num_cores_allocated": 1,
                "read": [
                    {
                        "end": 109.67742005806635,
                        "id": "file_8_0",
                        "start": 6.761567010309279e-17
                    }
                ],
                "task_id": "task_8_0",
                "terminated": -1.0,
                "whole_task": {
                    "end": 130.5290329751613,
                    "start": 6.761567010309279e-17
                },
                "write": [
                    {
                        "end": 130.5290329751613,
                        "id": "file_8_1",
                        "start": 114.07742005806635
                    }
                ]
            },
            {
                "color": "",
                "compute": {
                    "end": 151.38064590731554,
                    "start": 146.98064590731553
                },
                "execution_host": {
                    "cores": 32,
                    "flop_rate": 1000000000.0,
                    "hostname": "host01",
                    "memory": 268000000000.0
                },
                "failed": -1.0,
                "num_cores_allocated": 1,
                "read": [
                    {
                        "end": 146.98064590731553,
                        "id": "file_8_1",
                        "start": 130.5290329751613
                    }
                ],
                "task_id": "task_8_1",
                "terminated": -1.0,
                "whole_task": {
                    "end": 229.84883086537764,
                    "start": 130.5290329751613
                },
                "write": [
                    {
                        "end": 229.84883086537764,
                        "id": "file_8_2",
                        "start": 151.38064590731554
                    }
                ]
            },
            {
                "color": "",
                "compute": {
                    "end": 249.96968933838883,
                    "start": 245.56968933838883
                },
                "execution_host": {
                    "cores": 32,
                    "flop_rate": 1000000000.0,
                    "hostname": "host01",
                    "memory": 268000000000.0
                },
                "failed": -1.0,
                "num_cores_allocated": 1,
                "read": [
                    {
                        "end": 245.56968933838883,
                        "id": "file_8_2",
                        "start": 229.84883086537764
                    }
                ],
                "task_id": "task_8_2",
                "terminated": -1.0,
                "whole_task": {
                    "end": 328.6265771975278,
                    "start": 229.84883086537764
                },
                "write": [
                    {
                        "end": 328.6265771975278,
                        "id": "file_8_3",
                        "start": 249.96968933838883
                    }
                ]
            },
            {
                "color": "",
                "compute": {
                    "end": 114.07742005806635,
                    "start": 109.67742005806635
                },
                "execution_host": {
                    "cores": 32,
                    "flop_rate": 1000000000.0,
                    "hostname": "host01",
                    "memory": 268000000000.0
                },
                "failed": -1.0,
                "num_cores_allocated": 1,
                "read": [
                    {
                        "end": 109.67742005806635,
                        "id": "file_9_0",
                        "start": 7.204948453608248e-17
                    }
                ],
                "task_id": "task_9_0",
                "terminated": -1.0,
                "whole_task": {
                    "end": 130.5290329751613,
                    "start": 7.204948453608248e-17
                },
                "write": [
                    {
                        "end": 130.5290329751613,
                        "id": "file_9_1",
                        "start": 114.07742005806635
                    }
                ]
            },
            {
                "color": "",
                "compute": {
                    "end": 151.38064590731554,
                    "start": 146.98064590731553
                },
                "execution_host": {
                    "cores": 32,
                    "flop_rate": 1000000000.0,
                    "hostname": "host01",
                    "memory": 268000000000.0
                },
                "failed": -1.0,
                "num_cores_allocated": 1,
                "read": [
                    {
                        "end": 146.98064590731553,
                        "id": "file_9_1",
                        "start": 130.5290329751613
                    }
                ],
                "task_id": "task_9_1",
                "terminated": -1.0,
                "whole_task": {
                    "end": 229.3591830564522,
                    "start": 130.5290329751613
                },
                "write": [
                    {
                        "end": 229.3591830564522,
                        "id": "file_9_2",
                        "start": 151.38064590731554
                    }
                ]
            },
            {
                "color": "",
                "compute": {
                    "end": 249.73003094548514,
                    "start": 245.33003094548513
                },
                "execution_host": {
                    "cores": 32,
                    "flop_rate": 1000000000.0,
                    "hostname": "host01",
                    "memory": 268000000000.0
                },
                "failed": -1.0,
                "num_cores_allocated": 1,
                "read": [
                    {
                        "end": 245.33003094548513,
                        "id": "file_9_2",
                        "start": 229.3591830564522
                    }
                ],
                "task_id": "task_9_2",
                "terminated": -1.0,
                "whole_task": {
                    "end": 330.17243006225823,
                    "start": 229.3591830564522
                },
                "write": [
                    {
                        "end": 330.17243006225823,
                        "id": "file_9_3",
                        "start": 249.73003094548514
                    }
                ]
            }
        ]
    }
}
