{
    "workflow_execution": {
        "tasks": [
            {
                "color": "",
                "compute": {
                    "end": 127.564134599288,
                    "start": 122.563939449288
                },
                "execution_host": {
                    "cores": 32,
                    "flop_rate": 1000000000.0,
                    "hostname": "host01",
                    "memory": 268000000000.0
                },
                "failed": -1.0,
                "num_cores_allocated": 1,
                "read": [
                    {
                        "end": 122.563939449288,
                        "id": "file_0_0",
                        "start": 0.00019726981948412205
                    }
                ],
                "task_id": "task_0_0",
                "terminated": -1.0,
                "whole_task": {
                    "end": 249.97046830240757,
                    "start": 0.00019726981948412205
                },
                "write": [
                    {
                        "end": 249.97046830240757,
                        "id": "file_0_1",
                        "start": 127.564134599288
                    }
                ]
            },
            {
                "color": "",
                "compute": {
                    "end": 377.55196340162473,
                    "start": 372.5517682516247
                },
                "execution_host": {
                    "cores": 32,
                    "flop_rate": 1000000000.0,
                    "hostname": "host01",
                    "memory": 268000000000.0
                },
                "failed": -1.0,
                "num_cores_allocated": 1,
                "read": [
                    {
                        "end": 372.5517682516247,
                        "id": "file_0_1",
                        "start": 249.9712531420465
                    }
                ],
                "task_id": "task_0_1",
                "terminated": -1.0,
                "whole_task": {
                    "end": 497.6837945910948,
                    "start": 249.9712531420465
                },
                "write": [
                    {
                        "end": 497.6837945910948,
                        "id": "file_0_2",
                        "start": 377.55196340162473
                    }
                ]
            },
            {
                "color": "",
                "compute": {
                    "end": 625.2656418577067,
                    "start": 620.2654467077067
                },
                "execution_host": {
                    "cores": 32,
                    "flop_rate": 1000000000.0,
                    "hostname": "host01",
                    "memory": 268000000000.0
                },
                "failed": -1.0,
                "num_cores_allocated": 1,
                "read": [
                    {
                        "end": 620.2654467077067,
                        "id": "file_0_2",
                        "start": 497.6845794307339
                    }
                ],
                "task_id": "task_0_2",
                "terminated": -1.0,
                "whole_task": {
                    "end": 709.2173185539101,
                    "start": 497.6845794307339
                },
                "write": [
                    {
                        "end": 709.2173185539101,
                        "id": "file_0_3",
                        "start": 625.2656418577067
                    }
                ]
            },
            {
                "color": "",
                "compute": {
                    "end": 127.57128813600406,
                    "start": 122.57109298600406
                },
                "execution_host": {
                    "cores": 32,
                    "flop_rate": 1000000000.0,
                    "hostname": "host01",
                    "memory": 268000000000.0
                },
                "failed": -1.0,
                "num_cores_allocated": 1,
                "read": [
                    {
                        "end": 122.57109298600406,
                        "id": "file_10_0",
                        "start": 0.0005918094584523661
                    }
                ],
                "task_id": "task_10_0",
                "terminated": -1.0,
                "whole_task": {
                    "end": 250.09999127599608,
                    "start": 0.0005918094584523661
                },
                "write": [
                    {
                        "end": 250.09999127599608,
                        "id": "file_10_1",
                        "start": 127.57128813600406
                    }
                ]
            },
            {
                "color": "",
                "compute": {
                    "end": 377.6747941212311,
                    "start": 372.6745989712311
                },
                "execution_host": {
                    "cores": 32,
                    "flop_rate": 1000000000.0,
                    "hostname": "host01",
                    "memory": 268000000000.0
                },
                "failed": -1.0,
                "num_cores_allocated": 1,
                "read": [
                    {
                        "end": 372.6745989712311,
                        "id": "file_10_1",
                        "start": 250.100776115635
                    }
                ],
                "task_id": "task_10_1",
                "terminated": -1.0,
                "whole_task": {
                    "end": 499.90955386850027,
                    "start": 250.100776115635
                },
                "write": [
                    {
                        "end": 499.90955386850027,
                        "id": "file_10_2",
                        "start": 377.6747941212311
                    }
                ]
            },
            {
                "color": "",
                "compute": {
                    "end": 627.3743952940079,
                    "start": 622.3742001440079
                },
                "execution_host": {
                    "cores": 32,
                    "flop_rate": 1000000000.0,
                    "hostname": "host01",
                    "memory": 268000000000.0
                },
                "failed": -1.0,
                "num_cores_allocated": 1,
                "read": [
                    {
                        "end": 622.3742001440079,
                        "id": "file_10_2",
                        "start": 499.91033870813936
                    }
                ],
                "task_id": "task_10_2",
                "terminated": -1.0,
                "whole_task": {
                    "end": 745.3974590779253,
                    "start": 499.91033870813936
                },
                "write": [
                    {
                        "end": 745.3974590779253,
                        "id": "file_10_3",
                        "start": 627.3743952940079
                    }
                ]
            },
            {
                "color": "",
                "compute": {
                    "end": 127.57469344476313,
                    "start": 122.57449829476313
                },
                "execution_host": {
                    "cores": 32,
                    "flop_rate": 1000000000.0,
                    "hostname": "host01",
                    "memory": 268000000000.0
                },
                "failed": -1.0,
                "num_cores_allocated": 1,
                "read": [
                    {
                        "end": 122.57449829476313,
                        "id": "file_11_0",
                        "start": 0.0009863490974206103
                    }
                ],
                "task_id": "task_11_0",
                "terminated": -1.0,
                "whole_task": {
                    "end": 250.13226550900055,
                    "start": 0.0009863490974206103
                },
                "write": [
                    {
                        "end": 250.13226550900055,
                        "id": "file_11_1",
                        "start": 127.57469344476313
                    }
                ]
            },
            {
                "color": "",
                "compute": {
                    "end": 377.70379081379457,
                    "start": 372.70359566379454
                },
                "execution_host": {
                    "cores": 32,
                    "flop_rate": 1000000000.0,
                    "hostname": "host01",
                    "memory": 268000000000.0
                },
                "failed": -1.0,
                "num_cores_allocated": 1,
                "read": [
                    {
                        "end": 372.70359566379454,
                        "id": "file_11_1",
                        "start": 250.13305034863947
                    }
                ],
                "task_id": "task_11_1",
                "terminated": -1.0,
                "whole_task": {
                    "end": 500.18521626238487,
                    "start": 250.13305034863947
                },
                "write": [
                    {
                        "end": 500.18521626238487,
                        "id": "file_11_2",
                        "start": 377.70379081379457
                    }
                ]
            },
            {
                "color": "",
                "compute": {
                    "end": 627.6211601807657,
                    "start": 622.6209650307658
                },
                "execution_host": {
                    "cores": 32,
                    "flop_rate": 1000000000.0,
                    "hostname": "host01",
                    "memory": 268000000000.0
                },
                "failed": -1.0,
                "num_cores_allocated": 1,
                "read": [
                    {
                        "end": 622.6209650307658,
                        "id": "file_11_2",
                        "start": 500.18600110202397
                    }
                ],
                "task_id": "task_11_2",
                "terminated": -1.0,
                "whole_task": {
                    "end": 747.4949545945859,
                    "start": 500.18600110202397
                },
                "write": [
                    {
                        "end": 747.4949545945859,
                        "id": "file_11_3",
                        "start": 627.6211601807657
                    }
                ]
            },
            {
                "color": "",
                "compute": {
                    "end": 127.5768494162685,
                    "start": 122.5766542662685
                },
                "execution_host": {
                    "cores": 32,
                    "flop_rate": 1000000000.0,
                    "hostname": "host01",
                    "memory": 268000000000.0
                },
                "failed": -1.0,
                "num_cores_allocated": 1,
                "read": [
                    {
                        "end": 122.5766542662685,
                        "id": "file_12_0",
                        "start": 0.0013808887363888547
                    }
                ],
                "task_id": "task_12_0",
                "terminated": -1.0,
                "whole_task": {
                    "end": 250.14584379902152,
                    "start": 0.0013808887363888547
                },
                "write": [
                    {
                        "end": 250.14584379902152,
                        "id": "file_12_1",
                        "start": 127.5768494162685
                    }
                ]
            },
            {
                "color": "",
                "compute": {
                    "end": 377.7153410171774,
                    "start": 372.7151458671774
                },
                "execution_host": {
                    "cores": 32,
                    "flop_rate": 1000000000.0,
                    "hostname": "host01",
                    "memory": 268000000000.0
                },
                "failed": -1.0,
                "num_cores_allocated": 1,
                "read": [
                    {
                        "end": 372.7151458671774,
                        "id": "file_12_1",
                        "start": 250.14662863866045
                    }
                ],
                "task_id": "task_12_1",
                "terminated": -1.0,
                "whole_task": {
                    "end": 500.25829132124403,
                    "start": 250.14662863866045
                },
                "write": [
                    {
                        "end": 500.25829132124403,
                        "id": "file_12_2",
                        "start": 377.7153410171774
                    }
                ]
            },
            {
                "color": "",
                "compute": {
                    "end": 627.6828124688143,
                    "start": 622.6826173188143
                },
                "execution_host": {
                    "cores": 32,
                    "flop_rate": 1000000000.0,
                    "hostname": "host01",
                    "memory": 268000000000.0
                },
                "failed": -1.0,
                "num_cores_allocated": 1,
                "read": [
                    {
                        "end": 622.6826173188143,
                        "id": "file_12_2",
                        "start": 500.2590761608831
                    }
                ],
                "task_id": "task_12_2",
                "terminated": -1.0,
                "whole_task": {
                    "end": 747.8237633087614,
                    "start": 500.2590761608831
                },
                "write": [
                    {
                        "end": 747.8237633087614,
                        "id": "file_12_3",
                        "start": 627.6828124688143
                    }
                ]
            },
            {
                "color": "",
                "compute": {
                    "end": 127.5783805879308,
                    "start": 122.5781854379308
                },
                "execution_host": {
                    "cores": 32,
                    "flop_rate": 1000000000.0,
                    "hostname": "host01",
                    "memory": 268000000000.0
                },
                "failed": -1.0,
                "num_cores_allocated": 1,
                "read": [
                    {
                        "end": 122.5781854379308,
                        "id": "file_13_0",
                        "start": 0.001775428375357099
                    }
                ],
                "task_id": "task_13_0",
                "terminated": -1.0,
                "whole_task": {
                    "end": 250.15304062453595,
                    "start": 0.001775428375357099
                },
                "write": [
                    {
                        "end": 250.15304062453595,
                        "id": "file_13_1",
                        "start": 127.5783805879308
                    }
                ]
            },
            {
                "color": "",
                "compute": {
                    "end": 377.72113457970005,
                    "start": 372.7209394297
                },
                "execution_host": {
                    "cores": 32,
                    "flop_rate": 1000000000.0,
                    "hostname": "host01",
                    "memory": 268000000000.0
                },
                "failed": -1.0,
                "num_cores_allocated": 1,
                "read": [
                    {
                        "end": 372.7209394297,
                        "id": "file_13_1",
                        "start": 250.15382546417487
                    }
                ],
                "task_id": "task_13_1",
                "terminated": -1.0,
                "whole_task": {
                    "end": 500.28573464105415,
                    "start": 250.15382546417487
                },
                "write": [
                    {
                        "end": 500.28573464105415,
                        "id": "file_13_2",
                        "start": 377.72113457970005
                    }
                ]
            },
            {
                "color": "",
                "compute": {
                    "end": 627.7045898506533,
                    "start": 622.7043947006533
                },
                "execution_host": {
                    "cores": 32,
                    "flop_rate": 1000000000.0,
                    "hostname": "host01",
                    "memory": 268000000000.0
                },
                "failed": -1.0,
                "num_cores_allocated": 1,
                "read": [
                    {
                        "end": 622.7043947006533,
                        "id": "file_13_2",
                        "start": 500.28651948069324
                    }
                ],
                "task_id": "task_13_2",
                "terminated": -1.0,
                "whole_task": {
                    "end": 747.9054278390422,
                    "start": 500.28651948069324
                },
                "write": [
                    {
                        "end": 747.9054278390422,
                        "id": "file_13_3",
                        "start": 627.7045898506533
                    }
                ]
            },
            {
                "color": "",
                "compute": {
                    "end": 127.57953700137166,
                    "start": 122.57934185137167
                },
                "execution_host": {
                    "cores": 32,
                    "flop_rate": 1000000000.0,
                    "hostname": "host01",
                    "memory": 268000000000.0
                },
                "failed": -1.0,
                "num_cores_allocated": 1,
                "read": [
                    {
                        "end": 122.57934185137167,
                        "id": "file_14_0",
                        "start": 0.002169968014325343
                    }
                ],
                "task_id": "task_14_0",
                "terminated": -1.0,
                "whole_task": {
                    "end": 250.1573587661794,
                    "start": 0.002169968014325343
                },
                "write": [
                    {
                        "end": 250.1573587661794,
                        "id": "file_14_1",
                        "start": 127.57953700137166
                    }
                ]
            },
            {
                "color": "",
                "compute": {
                    "end": 377.7244242110399,
                    "start": 372.72422906103986
                },
                "execution_host": {
                    "cores": 32,
                    "flop_rate": 1000000000.0,
                    "hostname": "host01",
                    "memory": 268000000000.0
                },
                "failed": -1.0,
                "num_cores_allocated": 1,
                "read": [
                    {
                        "end": 372.72422906103986,
                        "id": "file_14_1",
                        "start": 250.15814360581834
                    }
                ],
                "task_id": "task_14_1",
                "terminated": -1.0,
                "whole_task": {
                    "end": 500.2981590423754,
                    "start": 250.15814360581834
                },
                "write": [
                    {
                        "end": 500.2981590423754,
                        "id": "file_14_2",
                        "start": 377.7244242110399
                    }
                ]
            },
            {
                "color": "",
                "compute": {
                    "end": 627.7138525443585,
                    "start": 622.7136573943585
                },
                "execution_host": {
                    "cores": 32,
                    "flop_rate": 1000000000.0,
                    "hostname": "host01",
                    "memory": 268000000000.0
                },
                "failed": -1.0,
                "num_cores_allocated": 1,
                "read": [
                    {
                        "end": 622.7136573943585,
                        "id": "file_14_2",
                        "start": 500.2989438820145
                    }
                ],
                "task_id": "task_14_2",
                "terminated": -1.0,
                "whole_task": {
                    "end": 747.931363163585,
                    "start": 500.2989438820145
                },
                "write": [
                    {
                        "end": 747.931363163585,
                        "id": "file_14_3",
                        "start": 627.7138525443585
                    }
                ]
            },
            {
                "color": "",
                "compute": {
                    "end": 127.58044355083403,
                    "start": 122.58024840083404
                },
                "execution_host": {
                    "cores": 32,
                    "flop_rate": 1000000000.0,
                    "hostname": "host01",
                    "memory": 268000000000.0
                },
                "failed": -1.0,
                "num_cores_allocated": 1,
                "read": [
                    {
                        "end": 122.58024840083404,
                        "id": "file_15_0",
                        "start": 0.002564507653293587
                    }
                ],
                "task_id": "task_15_0",
                "terminated": -1.0,
                "whole_task": {
                    "end": 250.16015331212395,
                    "start": 0.002564507653293587
                },
                "write": [
                    {
                        "end": 250.16015331212395,
                        "id": "file_15_1",
                        "start": 127.58044355083403
                    }
                ]
            },
            {
                "color": "",
                "compute": {
                    "end": 377.72644012878186,
                    "start": 372.72624497878184
                },
                "execution_host": {
                    "cores": 32,
                    "flop_rate": 1000000000.0,
                    "hostname": "host01",
                    "memory": 268000000000.0
                },
                "failed": -1.0,
                "num_cores_allocated": 1,
                "read": [
                    {
                        "end": 372.72624497878184,
                        "id": "file_15_1",
                        "start": 250.16093815176288
                    }
                ],
                "task_id": "task_15_1",
                "terminated": -1.0,
                "whole_task": {
                    "end": 500.30446655741963,
                    "start": 250.16093815176288
                },
                "write": [
                    {
                        "end": 500.30446655741963,
                        "id": "file_15_2",
                        "start": 377.72644012878186
                    }
                ]
            },
            {
                "color": "",
                "compute": {
                    "end": 627.7182720810745,
                    "start": 622.7180769310745
                },
                "execution_host": {
                    "cores": 32,
                    "flop_rate": 1000000000.0,
                    "hostname": "host01",
                    "memory": 268000000000.0
                },
                "failed": -1.0,
                "num_cores_allocated": 1,
                "read": [
                    {
                        "end": 622.7180769310745,
                        "id": "file_15_2",
                        "start": 500.3052513970587
                    }
                ],
                "task_id": "task_15_2",
                "terminated": -1.0,
                "whole_task": {
                    "end": 747.9409388140496,
                    "start": 500.3052513970587
                },
                "write": [
                    {
                        "end": 747.9409388140496,
                        "id": "file_15_3",
                        "start": 627.7182720810745
                    }
                ]
            },
            {
                "color": "",
                "compute": {
                    "end": 127.58117171927051,
                    "start": 122.58097656927052
                },
                "execution_host": {
                    "cores": 32,
                    "flop_rate": 1000000000.0,
                    "hostname": "host01",
                    "memory": 268000000000.0
                },
                "failed": -1.0,
                "num_cores_allocated": 1,
                "read": [
                    {
                        "end": 122.58097656927052,
                        "id": "file_16_0",
                        "start": 0.002959047292261831
                    }
                ],
                "task_id": "task_16_0",
                "terminated": -1.0,
                "whole_task": {
                    "end": 250.16205371398246,
                    "start": 0.002959047292261831
                },
                "write": [
                    {
                        "end": 250.16205371398246,
                        "id": "file_16_1",
                        "start": 127.58117171927051
                    }
                ]
            },
            {
                "color": "",
                "compute": {
                    "end": 377.7277418638851,
                    "start": 372.7275467138851
                },
                "execution_host": {
                    "cores": 32,
                    "flop_rate": 1000000000.0,
                    "hostname": "host01",
                    "memory": 268000000000.0
                },
                "failed": -1.0,
                "num_cores_allocated": 1,
                "read": [
                    {
                        "end": 372.7275467138851,
                        "id": "file_16_1",
                        "start": 250.16283855362138
                    }
                ],
                "task_id": "task_16_1",
                "terminated": -1.0,
                "whole_task": {
                    "end": 500.3079237743322,
                    "start": 250.16283855362138
                },
                "write": [
                    {
                        "end": 500.3079237743322,
                        "id": "file_16_2",
                        "start": 377.7277418638851
                    }
                ]
            },
            {
                "color": "",
                "compute": {
                    "end": 627.7205554547304,
                    "start": 622.7203603047304
                },
                "execution_host": {
                    "cores": 32,
                    "flop_rate": 1000000000.0,
                    "hostname": "host01",
                    "memory": 268000000000.0
                },
                "failed": -1.0,
                "num_cores_allocated": 1,
                "read": [
                    {
                        "end": 622.7203603047304,
                        "id": "file_16_2",
                        "start": 500.3087086139713
                    }
                ],
                "task_id": "task_16_2",
                "terminated": -1.0,
                "whole_task": {
                    "end": 747.9448532516108,
                    "start": 500.3087086139713
                },
                "write": [
                    {
                        "end": 747.9448532516108,
                        "id": "file_16_3",
                        "start": 627.7205554547304
                    }
                ]
            },
            {
                "color": "",
                "compute": {
                    "end": 127.58176350529202,
                    "start": 122.58156835529202
                },
                "execution_host": {
                    "cores": 32,
                    "flop_rate": 1000000000.0,
                    "hostname": "host01",
                    "memory": 268000000000.0
                },
                "failed": -1.0,
                "num_cores_allocated": 1,
                "read": [
                    {
                        "end": 122.58156835529202,
                        "id": "file_17_0",
                        "start": 0.003353586931230075
                    }
                ],
                "task_id": "task_17_0",
                "terminated": -1.0,
                "whole_task": {
                    "end": 250.16323097344085,
                    "start": 0.003353586931230075
                },
                "write": [
                    {
                        "end": 250.16323097344085,
                        "id": "file_17_1",
                        "start": 127.58176350529202
                    }
                ]
            },
            {
                "color": "",
                "compute": {
                    "end": 377.7285220762507,
                    "start": 372.7283269262507
                },
                "execution_host": {
                    "cores": 32,
                    "flop_rate": 1000000000.0,
                    "hostname": "host01",
                    "memory": 268000000000.0
                },
                "failed": -1.0,
                "num_cores_allocated": 1,
                "read": [
                    {
                        "end": 372.7283269262507,
                        "id": "file_17_1",
                        "start": 250.16401581307977
                    }
                ],
                "task_id": "task_17_1",
                "terminated": -1.0,
                "whole_task": {
                    "end": 500.3097005740405,
                    "start": 250.16401581307977
                },
                "write": [
                    {
                        "end": 500.3097005740405,
                        "id": "file_17_2",
                        "start": 377.7285220762507
                    }
                ]
            },
            {
                "color": "",
                "compute": {
                    "end": 627.7216799790807,
                    "start": 622.7214848290807
                },
                "execution_host": {
                    "cores": 32,
                    "flop_rate": 1000000000.0,
                    "hostname": "host01",
                    "memory": 268000000000.0
                },
                "failed": -1.0,
                "num_cores_allocated": 1,
                "read": [
                    {
                        "end": 622.7214848290807,
                        "id": "file_17_2",
                        "start": 500.3104854136796
                    }
                ],
                "task_id": "task_17_2",
                "terminated": -1.0,
                "whole_task": {
                    "end": 747.9463993601397,
                    "start": 500.3104854136796
                },
                "write": [
                    {
                        "end": 747.9463993601397,
                        "id": "file_17_3",
                        "start": 627.7216799790807
                    }
                ]
            },
            {
                "color": "",
                "compute": {
                    "end": 127.5822482079802,
                    "start": 122.5820530579802
                },
                "execution_host": {
                    "cores": 32,
                    "flop_rate": 1000000000.0,
                    "hostname": "host01",
                    "memory": 268000000000.0
                },
                "failed": -1.0,
                "num_cores_allocated": 1,
                "read": [
                    {
                        "end": 122.5820530579802,
                        "id": "file_18_0",
                        "start": 0.0037481265701983187
                    }
                ],
                "task_id": "task_18_0",
                "terminated": -1.0,
                "whole_task": {
                    "end": 250.16435226261513,
                    "start": 0.0037481265701983187
                },
                "write": [
                    {
                        "end": 250.16435226261513,
                        "id": "file_18_1",
                        "start": 127.5822482079802
                    }
                ]
            },
            {
                "color": "",
                "compute": {
                    "end": 377.7292237267883,
                    "start": 372.72902857678827
                },
                "execution_host": {
                    "cores": 32,
                    "flop_rate": 1000000000.0,
                    "hostname": "host01",
                    "memory": 268000000000.0
                },
                "failed": -1.0,
                "num_cores_allocated": 1,
                "read": [
                    {
                        "end": 372.72902857678827,
                        "id": "file_18_1",
                        "start": 250.16513710225405
                    }
                ],
                "task_id": "task_18_1",
                "terminated": -1.0,
                "whole_task": {
                    "end": 500.31110575339164,
                    "start": 250.16513710225405
                },
                "write": [
                    {
                        "end": 500.31110575339164,
                        "id": "file_18_2",
                        "start": 377.7292237267883
                    }
                ]
            },
            {
                "color": "",
                "compute": {
                    "end": 627.7225373957474,
                    "start": 622.7223422457474
                },
                "execution_host": {
                    "cores": 32,
                    "flop_rate": 1000000000.0,
                    "hostname": "host01",
                    "memory": 268000000000.0
                },
                "failed": -1.0,
                "num_cores_allocated": 1,
                "read": [
                    {
                        "end": 622.7223422457474,
                        "id": "file_18_2",
                        "start": 500.31189059303074
                    }
                ],
                "task_id": "task_18_2",
                "terminated": -1.0,
                "whole_task": {
                    "end": 747.9473521444752,
                    "start": 500.31189059303074
                },
                "write": [
                    {
                        "end": 747.9473521444752,
                        "id": "file_18_3",
                        "start": 627.7225373957474
                    }
                ]
            },
            {
                "color": "",
                "compute": {
                    "end": 127.58265067142105,
                    "start": 122.58245552142105
                },
                "execution_host": {
                    "cores": 32,
                    "flop_rate": 1000000000.0,
                    "hostname": "host01",
                    "memory": 268000000000.0
                },
                "failed": -1.0,
                "num_cores_allocated": 1,
                "read": [
                    {
                        "end": 122.58245552142105,
                        "id": "file_1_0",
                        "start": 0.004142666209166563
                    }
                ],
                "task_id": "task_1_0",
                "terminated": -1.0,
                "whole_task": {
                    "end": 250.1650618932603,
                    "start": 0.004142666209166563
                },
                "write": [
                    {
                        "end": 250.1650618932603,
                        "id": "file_1_1",
                        "start": 127.58265067142105
                    }
                ]
            },
            {
                "color": "",
                "compute": {
                    "end": 377.729589089154,
                    "start": 372.72939393915397
                },
                "execution_host": {
                    "cores": 32,
                    "flop_rate": 1000000000.0,
                    "hostname": "host01",
                    "memory": 268000000000.0
                },
                "failed": -1.0,
                "num_cores_allocated": 1,
                "read": [
                    {
                        "end": 372.72939393915397,
                        "id": "file_1_1",
                        "start": 250.16572679189298
                    }
                ],
                "task_id": "task_1_1",
                "terminated": -1.0,
                "whole_task": {
                    "end": 500.31176343564977,
                    "start": 250.16572679189298
                },
                "write": [
                    {
                        "end": 500.31176343564977,
                        "id": "file_1_2",
                        "start": 377.729589089154
                    }
                ]
            },
            {
                "color": "",
                "compute": {
                    "end": 627.7228879220914,
                    "start": 622.7226927720915
                },
                "execution_host": {
                    "cores": 32,
                    "flop_rate": 1000000000.0,
                    "hostname": "host01",
                    "memory": 268000000000.0
                },
                "failed": -1.0,
                "num_cores_allocated": 1,
                "read": [
                    {
                        "end": 622.7226927720915,
                        "id": "file_1_2",
                        "start": 500.3124802826698
                    }
                ],
                "task_id": "task_1_2",
                "terminated": -1.0,
                "whole_task": {
                    "end": 747.9476676041526,
                    "start": 500.3124802826698
                },
                "write": [
                    {
                        "end": 747.9476676041526,
                        "id": "file_1_3",
                        "start": 627.7228879220914
                    }
                ]
            },
            {
                "color": "",
                "compute": {
                    "end": 127.58298581496943,
                    "start": 122.58279066496944
                },
                "execution_host": {
                    "cores": 32,
                    "flop_rate": 1000000000.0,
                    "hostname": "host01",
                    "memory": 268000000000.0
                },
                "failed": -1.0,
                "num_cores_allocated": 1,
                "read": [
                    {
                        "end": 122.58279066496944,
                        "id": "file_2_0",
                        "start": 0.004537205848134807
                    }
                ],
                "task_id": "task_2_0",
                "terminated": -1.0,
                "whole_task": {
                    "end": 250.1655295220735,
                    "start": 0.004537205848134807
                },
                "write": [
                    {
                        "end": 250.1655295220735,
                        "id": "file_2_1",
                        "start": 127.58298581496943
                    }
                ]
            },
            {
                "color": "",
                "compute": {
                    "end": 377.73000540689594,
                    "start": 372.7298102568959
                },
                "execution_host": {
                    "cores": 32,
                    "flop_rate": 1000000000.0,
                    "hostname": "host01",
                    "memory": 268000000000.0
                },
                "failed": -1.0,
                "num_cores_allocated": 1,
                "read": [
                    {
                        "end": 372.7298102568959,
                        "id": "file_2_1",
                        "start": 250.1663164815319
                    }
                ],
                "task_id": "task_2_1",
                "terminated": -1.0,
                "whole_task": {
                    "end": 500.3122830128503,
                    "start": 250.1663164815319
                },
                "write": [
                    {
                        "end": 500.3122830128503,
                        "id": "file_2_2",
                        "start": 377.73000540689594
                    }
                ]
            },
            {
                "color": "",
                "compute": {
                    "end": 627.7232259366077,
                    "start": 622.7230307866078
                },
                "execution_host": {
                    "cores": 32,
                    "flop_rate": 1000000000.0,
                    "hostname": "host01",
                    "memory": 268000000000.0
                },
                "failed": -1.0,
                "num_cores_allocated": 1,
                "read": [
                    {
                        "end": 622.7230307866078,
                        "id": "file_2_2",
                        "start": 500.3130699723089
                    }
                ],
                "task_id": "task_2_2",
                "terminated": -1.0,
                "whole_task": {
                    "end": 747.9479134380235,
                    "start": 500.3130699723089
                },
                "write": [
                    {
                        "end": 747.9479134380235,
                        "id": "file_2_3",
                        "start": 627.7232259366077
                    }
                ]
            },
            {
                "color": "",
                "compute": {
                    "end": 127.5832647031415,
                    "start": 122.5830695531415
                },
                "execution_host": {
                    "cores": 32,
                    "flop_rate": 1000000000.0,
                    "hostname": "host01",
                    "memory": 268000000000.0
                },
                "failed": -1.0,
                "num_cores_allocated": 1,
                "read": [
                    {
                        "end": 122.5830695531415,
                        "id": "file_3_0",
                        "start": 0.004931745487103051
                    }
                ],
                "task_id": "task_3_0",
                "terminated": -1.0,
                "whole_task": {
                    "end": 250.165965885979,
                    "start": 0.004931745487103051
                },
                "write": [
                    {
                        "end": 250.165965885979,
                        "id": "file_3_1",
                        "start": 127.5832647031415
                    }
                ]
            },
            {
                "color": "",
                "compute": {
                    "end": 377.73040569845074,
                    "start": 372.7302105484507
                },
                "execution_host": {
                    "cores": 32,
                    "flop_rate": 1000000000.0,
                    "hostname": "host01",
                    "memory": 268000000000.0
                },
                "failed": -1.0,
                "num_cores_allocated": 1,
                "read": [
                    {
                        "end": 372.7302105484507,
                        "id": "file_3_1",
                        "start": 250.16690617117084
                    }
                ],
                "task_id": "task_3_1",
                "terminated": -1.0,
                "whole_task": {
                    "end": 500.31287270248936,
                    "start": 250.16690617117084
                },
                "write": [
                    {
                        "end": 500.31287270248936,
                        "id": "file_3_2",
                        "start": 377.73040569845074
                    }
                ]
            },
            {
                "color": "",
                "compute": {
                    "end": 627.7235723075754,
                    "start": 622.7233771575754
                },
                "execution_host": {
                    "cores": 32,
                    "flop_rate": 1000000000.0,
                    "hostname": "host01",
                    "memory": 268000000000.0
                },
                "failed": -1.0,
                "num_cores_allocated": 1,
                "read": [
                    {
                        "end": 622.7233771575754,
                        "id": "file_3_2",
                        "start": 500.31365966194795
                    }
                ],
                "task_id": "task_3_2",
                "terminated": -1.0,
                "whole_task": {
                    "end": 747.9481154826472,
                    "start": 500.31365966194795
                },
                "write": [
                    {
                        "end": 747.9481154826472,
                        "id": "file_3_3",
                        "start": 627.7235723075754
                    }
                ]
            },
            {
                "color": "",
                "compute": {
                    "end": 127.58349601228127,
                    "start": 122.58330086228128
                },
                "execution_host": {
                    "cores": 32,
                    "flop_rate": 1000000000.0,
                    "hostname": "host01",
                    "memory": 268000000000.0
                },
                "failed": -1.0,
                "num_cores_allocated": 1,
                "read": [
                    {
                        "end": 122.58330086228128,
                        "id": "file_4_0",
                        "start": 0.005326285126071295
                    }
                ],
                "task_id": "task_4_0",
                "terminated": -1.0,
                "whole_task": {
                    "end": 250.16611921171244,
                    "start": 0.005326285126071295
                },
                "write": [
                    {
                        "end": 250.16611921171244,
                        "id": "file_4_1",
                        "start": 127.58349601228127
                    }
                ]
            },
            {
                "color": "",
                "compute": {
                    "end": 377.7307258398486,
                    "start": 372.7305306898486
                },
                "execution_host": {
                    "cores": 32,
                    "flop_rate": 1000000000.0,
                    "hostname": "host01",
                    "memory": 268000000000.0
                },
                "failed": -1.0,
                "num_cores_allocated": 1,
                "read": [
                    {
                        "end": 372.7305306898486,
                        "id": "file_4_1",
                        "start": 250.16749586080977
                    }
                ],
                "task_id": "task_4_1",
                "terminated": -1.0,
                "whole_task": {
                    "end": 500.3133818922014,
                    "start": 250.16749586080977
                },
                "write": [
                    {
                        "end": 500.3133818922014,
                        "id": "file_4_2",
                        "start": 377.7307258398486
                    }
                ]
            },
            {
                "color": "",
                "compute": {
                    "end": 627.7239003070378,
                    "start": 622.7237051570378
                },
                "execution_host": {
                    "cores": 32,
                    "flop_rate": 1000000000.0,
                    "hostname": "host01",
                    "memory": 268000000000.0
                },
                "failed": -1.0,
                "num_cores_allocated": 1,
                "read": [
                    {
                        "end": 622.7237051570378,
                        "id": "file_4_2",
                        "start": 500.314249351587
                    }
                ],
                "task_id": "task_4_2",
                "terminated": -1.0,
                "whole_task": {
                    "end": 747.9481154826472,
                    "start": 500.314249351587
                },
                "write": [
                    {
                        "end": 747.9481154826472,
                        "id": "file_4_3",
                        "start": 627.7239003070378
                    }
                ]
            },
            {
                "color": "",
                "compute": {
                    "end": 127.58349601228127,
                    "start": 122.58330086228128
                },
                "execution_host": {
                    "cores": 32,
                    "flop_rate": 1000000000.0,
                    "hostname": "host01",
                    "memory": 268000000000.0
                },
                "failed": -1.0,
                "num_cores_allocated": 1,
                "read": [
                    {
                        "end": 122.58330086228128,
                        "id": "file_5_0",
                        "start": 0.005720824765039539
                    }
                ],
                "task_id": "task_5_0",
                "terminated": -1.0,
                "whole_task": {
                    "end": 250.16611921171244,
                    "start": 0.005720824765039539
                },
                "write": [
                    {
                        "end": 250.16611921171244,
                        "id": "file_5_1",
                        "start": 127.58349601228127
                    }
                ]
            },
            {
                "color": "",
                "compute": {
                    "end": 377.73098493823574,
                    "start": 372.7307897882357
                },
                "execution_host": {
                    "cores": 32,
                    "flop_rate": 1000000000.0,
                    "hostname": "host01",
                    "memory": 268000000000.0
                },
                "failed": -1.0,
                "num_cores_allocated": 1,
                "read": [
                    {
                        "end": 372.7307897882357,
                        "id": "file_5_1",
                        "start": 250.1680855504487
                    }
                ],
                "task_id": "task_5_1",
                "terminated": -1.0,
                "whole_task": {
                    "end": 500.31367922169835,
                    "start": 250.1680855504487
                },
                "write": [
                    {
                        "end": 500.31367922169835,
                        "id": "file_5_2",
                        "start": 377.73098493823574
                    }
                ]
            },
            {
                "color": "",
                "compute": {
                    "end": 627.7241593925216,
                    "start": 622.7239642425217
                },
                "execution_host": {
                    "cores": 32,
                    "flop_rate": 1000000000.0,
                    "hostname": "host01",
                    "memory": 268000000000.0
                },
                "failed": -1.0,
                "num_cores_allocated": 1,
                "read": [
                    {
                        "end": 622.7239642425217,
                        "id": "file_5_2",
                        "start": 500.3148390412261
                    }
                ],
                "task_id": "task_5_2",
                "terminated": -1.0,
                "whole_task": {
                    "end": 747.9483594013913,
                    "start": 500.3148390412261
                },
                "write": [
                    {
                        "end": 747.9483594013913,
                        "id": "file_5_3",
                        "start": 627.7241593925216
                    }
                ]
            },
            {
                "color": "",
                "compute": {
                    "end": 127.58384160114788,
                    "start": 122.58364645114789
                },
                "execution_host": {
                    "cores": 32,
                    "flop_rate": 1000000000.0,
                    "hostname": "host01",
                    "memory": 268000000000.0
                },
                "failed": -1.0,
                "num_cores_allocated": 1,
                "read": [
                    {
                        "end": 122.58364645114789,
                        "id": "file_6_0",
                        "start": 0.006115364404007783
                    }
                ],
                "task_id": "task_6_0",
                "terminated": -1.0,
                "whole_task": {
                    "end": 250.16659159404352,
                    "start": 0.006115364404007783
                },
                "write": [
                    {
                        "end": 250.16659159404352,
                        "id": "file_6_1",
                        "start": 127.58384160114788
                    }
                ]
            },
            {
                "color": "",
                "compute": {
                    "end": 377.7311911419992,
                    "start": 372.7309959919992
                },
                "execution_host": {
                    "cores": 32,
                    "flop_rate": 1000000000.0,
                    "hostname": "host01",
                    "memory": 268000000000.0
                },
                "failed": -1.0,
                "num_cores_allocated": 1,
                "read": [
                    {
                        "end": 372.7309959919992,
                        "id": "file_6_1",
                        "start": 250.16867524008762
                    }
                ],
                "task_id": "task_6_1",
                "terminated": -1.0,
                "whole_task": {
                    "end": 500.31389918030055,
                    "start": 250.16867524008762
                },
                "write": [
                    {
                        "end": 500.31389918030055,
                        "id": "file_6_2",
                        "start": 377.7311911419992
                    }
                ]
            },
            {
                "color": "",
                "compute": {
                    "end": 627.7243656070377,
                    "start": 622.7241704570378
                },
                "execution_host": {
                    "cores": 32,
                    "flop_rate": 1000000000.0,
                    "hostname": "host01",
                    "memory": 268000000000.0
                },
                "failed": -1.0,
                "num_cores_allocated": 1,
                "read": [
                    {
                        "end": 622.7241704570378,
                        "id": "file_6_2",
                        "start": 500.31542873086516
                    }
                ],
                "task_id": "task_6_2",
                "terminated": -1.0,
                "whole_task": {
                    "end": 747.9483594013913,
                    "start": 500.31542873086516
                },
                "write": [
                    {
                        "end": 747.9483594013913,
                        "id": "file_6_3",
                        "start": 627.7243656070377
                    }
                ]
            },
            {
                "color": "",
                "compute": {
                    "end": 127.58384160114788,
                    "start": 122.58364645114789
                },
                "execution_host": {
                    "cores": 32,
                    "flop_rate": 1000000000.0,
                    "hostname": "host01",
                    "memory": 268000000000.0
                },
                "failed": -1.0,
                "num_cores_allocated": 1,
                "read": [
                    {
                        "end": 122.58364645114789,
                        "id": "file_7_0",
                        "start": 0.006509904042976027
                    }
                ],
                "task_id": "task_7_0",
                "terminated": -1.0,
                "whole_task": {
                    "end": 250.16659159404352,
                    "start": 0.006509904042976027
                },
                "write": [
                    {
                        "end": 250.16659159404352,
                        "id": "file_7_1",
                        "start": 127.58384160114788
                    }
                ]
            },
            {
                "color": "",
                "compute": {
                    "end": 377.7311911419992,
                    "start": 372.7309959919992
                },
                "execution_host": {
                    "cores": 32,
                    "flop_rate": 1000000000.0,
                    "hostname": "host01",
                    "memory": 268000000000.0
                },
                "failed": -1.0,
                "num_cores_allocated": 1,
                "read": [
                    {
                        "end": 372.7309959919992,
                        "id": "file_7_1",
                        "start": 250.16926492972655
                    }
                ],
                "task_id": "task_7_1",
                "terminated": -1.0,
                "whole_task": {
                    "end": 500.31389918030055,
                    "start": 250.16926492972655
                },
                "write": [
                    {
                        "end": 500.31389918030055,
                        "id": "file_7_2",
                        "start": 377.7311911419992
                    }
                ]
            },
            {
                "color": "",
                "compute": {
                    "end": 627.7243656070377,
                    "start": 622.7241704570378
                },
                "execution_host": {
                    "cores": 32,
                    "flop_rate": 1000000000.0,
                    "hostname": "host01",
                    "memory": 268000000000.0
                },
                "failed": -1.0,
                "num_cores_allocated": 1,
                "read": [
                    {
                        "end": 622.7241704570378,
                        "id": "file_7_2",
                        "start": 500.31601842050424
                    }
                ],
                "task_id": "task_7_2",
                "terminated": -1.0,
                "whole_task": {
                    "end": 747.9483594013913,
                    "start": 500.31601842050424
                },
                "write": [
                    {
                        "end": 747.9483594013913,
                        "id": "file_7_3",
                        "start": 627.7243656070377
                    }
                ]
            },
            {
                "color": "",
                "compute": {
                    "end": 127.58405852319089,
                    "start": 122.5838633731909
                },
                "execution_host": {
                    "cores": 32,
                    "flop_rate": 1000000000.0,
                    "hostname": "host01",
                    "memory": 268000000000.0
                },
                "failed": -1.0,
                "num_cores_allocated": 1,
                "read": [
                    {
                        "end": 122.5838633731909,
                        "id": "file_8_0",
                        "start": 0.006904443681944271
                    }
                ],
                "task_id": "task_8_0",
                "terminated": -1.0,
                "whole_task": {
                    "end": 250.16670890135137,
                    "start": 0.006904443681944271
                },
                "write": [
                    {
                        "end": 250.16670890135137,
                        "id": "file_8_1",
                        "start": 127.58405852319089
                    }
                ]
            },
            {
                "color": "",
                "compute": {
                    "end": 377.7314699694186,
                    "start": 372.73127481941856
                },
                "execution_host": {
                    "cores": 32,
                    "flop_rate": 1000000000.0,
                    "hostname": "host01",
                    "memory": 268000000000.0
                },
                "failed": -1.0,
                "num_cores_allocated": 1,
                "read": [
                    {
                        "end": 372.73127481941856,
                        "id": "file_8_1",
                        "start": 250.16985461936548
                    }
                ],
                "task_id": "task_8_1",
                "terminated": -1.0,
                "whole_task": {
                    "end": 500.3140520817675,
                    "start": 250.16985461936548
                },
                "write": [
                    {
                        "end": 500.3140520817675,
                        "id": "file_8_2",
                        "start": 377.7314699694186
                    }
                ]
            },
            {
                "color": "",
                "compute": {
                    "end": 627.7246444366076,
                    "start": 622.7244492866076
                },
                "execution_host": {
                    "cores": 32,
                    "flop_rate": 1000000000.0,
                    "hostname": "host01",
                    "memory": 268000000000.0
                },
                "failed": -1.0,
                "num_cores_allocated": 1,
                "read": [
                    {
                        "end": 622.7244492866076,
                        "id": "file_8_2",
                        "start": 500.3166081101433
                    }
                ],
                "task_id": "task_8_2",
                "terminated": -1.0,
                "whole_task": {
                    "end": 747.9483594013913,
                    "start": 500.3166081101433
                },
                "write": [
                    {
                        "end": 747.9483594013913,
                        "id": "file_8_3",
                        "start": 627.7246444366076
                    }
                ]
            },
            {
                "color": "",
                "compute": {
                    "end": 127.58405852319089,
                    "start": 122.5838633731909
                },
                "execution_host": {
                    "cores": 32,
                    "flop_rate": 1000000000.0,
                    "hostname": "host01",
                    "memory": 268000000000.0
                },
                "failed": -1.0,
                "num_cores_allocated": 1,
                "read": [
                    {
                        "end": 122.5838633731909,
                        "id": "file_9_0",
                        "start": 0.007298983320912515
                    }
                ],
                "task_id": "task_9_0",
                "terminated": -1.0,
                "whole_task": {
                    "end": 250.16670890135137,
                    "start": 0.007298983320912515
                },
                "write": [
                    {
                        "end": 250.16670890135137,
                        "id": "file_9_1",
                        "start": 127.58405852319089
                    }
                ]
            },
            {
                "color": "",
                "compute": {
                    "end": 377.7314699694186,
                    "start": 372.73127481941856
                },
                "execution_host": {
                    "cores": 32,
                    "flop_rate": 1000000000.0,
                    "hostname": "host01",
                    "memory": 268000000000.0
                },
                "failed": -1.0,
                "num_cores_allocated": 1,
                "read": [
                    {
                        "end": 372.73127481941856,
                        "id": "file_9_1",
                        "start": 250.1704443090044
                    }
                ],
                "task_id": "task_9_1",
                "terminated": -1.0,
                "whole_task": {
                    "end": 500.3140520817675,
                    "start": 250.1704443090044
                },
                "write": [
                    {
                        "end": 500.3140520817675,
                        "id": "file_9_2",
                        "start": 377.7314699694186
                    }
                ]
            },
            {
                "color": "",
                "compute": {
                    "end": 627.7246444366076,
                    "start": 622.7244492866076
                },
                "execution_host": {
                    "cores": 32,
                    "flop_rate": 1000000000.0,
                    "hostname": "host01",
                    "memory": 268000000000.0
                },
                "failed": -1.0,
                "num_cores_allocated": 1,
                "read": [
                    {
                        "end": 622.7244492866076,
                        "id": "file_9_2",
                        "start": 500.3171977997824
                    }
                ],
                "task_id": "task_9_2",
                "terminated": -1.0,
                "whole_task": {
                    "end": 747.9483594013913,
                    "start": 500.3171977997824
                },
                "write": [
                    {
                        "end": 747.9483594013913,
                        "id": "file_9_3",
                        "start": 627.7246444366076
                    }
                ]
            }
        ]
    }
}
